flask_ligand_example/__init__.py
flask_ligand_example/models.py
flask_ligand_example/schemas.py
flask_ligand_example/views/__init__.py
flask_ligand_example/views/pet.py
flask_ligand_example-0.5.2.data/data/README.rst/README.rst
flask_ligand_example-0.5.2.dist-info/AUTHORS
flask_ligand_example-0.5.2.dist-info/LICENSE
flask_ligand_example-0.5.2.dist-info/METADATA
flask_ligand_example-0.5.2.dist-info/WHEEL
flask_ligand_example-0.5.2.dist-info/pbr.json
flask_ligand_example-0.5.2.dist-info/top_level.txt
flask_ligand_example-0.5.2.dist-info/RECORD
