Metadata-Version: 2.1
Name: flask-ligand-example
Version: 0.5.2
Summary: A simple example project on how to use the flask-ligand library.
Author: Ryan Gard
Author-email: ryan@gardiancapitol.com
License: GNU Affero General Public License v3
Project-URL: Changelog, https://github.com/cowofevil/flask-ligand-example/blob/main/CHANGELOG.md
Project-URL: Source, https://github.com/cowofevil/flask-ligand-example
Project-URL: Tracker, https://github.com/cowofevil/flask-ligand-example/issues
Keywords: flask
Classifier: Development Status :: 4 - Beta
Classifier: Intended Audience :: Developers
Classifier: Framework :: Flask
Classifier: Operating System :: MacOS :: MacOS X
Classifier: Operating System :: Microsoft :: Windows
Classifier: Operating System :: POSIX
Classifier: Natural Language :: English
Classifier: Programming Language :: Python :: 3
Classifier: Programming Language :: Python :: 3 :: Only
Classifier: Programming Language :: Python :: 3.10
Classifier: Programming Language :: Python :: 3.11
Classifier: Topic :: Software Development :: Libraries
Classifier: Topic :: Software Development :: Libraries :: Application Frameworks
Classifier: Typing :: Typed
Requires-Python: >=3.10
License-File: LICENSE
License-File: AUTHORS
Requires-Dist: flask-ligand (==0.8.1)
